Blunvato/__init__.py
Blunvato/courses.py
Blunvato/utils.py
blunvato-0.1.0.dist-info/METADATA
blunvato-0.1.0.dist-info/WHEEL
blunvato-0.1.0.dist-info/top_level.txt
blunvato-0.1.0.dist-info/RECORD
